{
  "highlightr-plugin:Blue": [
    {
      "modifiers": [
        "Alt",
        "Mod"
      ],
      "key": "B"
    }
  ],
  "highlightr-plugin:Red": [
    {
      "modifiers": [
        "Alt",
        "Mod"
      ],
      "key": "R"
    }
  ],
  "highlightr-plugin:Cyan": [
    {
      "modifiers": [
        "Alt",
        "Mod"
      ],
      "key": "C"
    }
  ],
  "highlightr-plugin:Green": [
    {
      "modifiers": [
        "Alt",
        "Mod"
      ],
      "key": "G"
    }
  ],
  "highlightr-plugin:Orange": [
    {
      "modifiers": [
        "Alt",
        "Mod"
      ],
      "key": "O"
    }
  ],
  "highlightr-plugin:Pink": [
    {
      "modifiers": [
        "Alt",
        "Mod"
      ],
      "key": "P"
    }
  ]
}